.flake8
LICENSE-APACHE
LICENSE-MIT
MANIFEST.in
Makefile
README.rst
mypy.ini
performance.png
pyproject.toml
setup.py
docs/conf.py
docs/index.rst
docs/api/index.rst
docs/dev/index.rst
docs/user/index.rst
examples/bench/echoclient.py
examples/bench/echoserver.py
examples/bench/rlserver.py
gerokgak.egg-info/PKG-INFO
gerokgak.egg-info/SOURCES.txt
gerokgak.egg-info/dependency_links.txt
gerokgak.egg-info/not-zip-safe
gerokgak.egg-info/requires.txt
gerokgak.egg-info/top_level.txt
tests/__init__.py
tests/__main__.py
tests/test_aiohttp.py
tests/test_base.py
tests/test_context.py
tests/test_cython.py
tests/test_dealloc.py
tests/test_dns.py
tests/test_executors.py
tests/test_fs_event.py
tests/test_libuv_api.py
tests/test_pipes.py
tests/test_process.py
tests/test_process_spawning.py
tests/test_regr1.py
tests/test_runner.py
tests/test_signals.py
tests/test_sockets.py
tests/test_sourcecode.py
tests/test_tcp.py
tests/test_testbase.py
tests/test_udp.py
tests/test_unix.py
tests/certs/ssl_cert.pem
tests/certs/ssl_key.pem
uvloop/__init__.py
uvloop/_noop.py
uvloop/_testbase.py
uvloop/_version.py
uvloop/cbhandles.pxd
uvloop/cbhandles.pyx
uvloop/dns.pyx
uvloop/errors.pyx
uvloop/loop.c
uvloop/loop.pxd
uvloop/loop.pyi
uvloop/loop.pyx
uvloop/lru.pyx
uvloop/pseudosock.pyx
uvloop/py.typed
uvloop/request.pxd
uvloop/request.pyx
uvloop/server.pxd
uvloop/server.pyx
uvloop/sslproto.pxd
uvloop/sslproto.pyx
uvloop/handles/async_.pxd
uvloop/handles/async_.pyx
uvloop/handles/basetransport.pxd
uvloop/handles/basetransport.pyx
uvloop/handles/check.pxd
uvloop/handles/check.pyx
uvloop/handles/fsevent.pxd
uvloop/handles/fsevent.pyx
uvloop/handles/handle.pxd
uvloop/handles/handle.pyx
uvloop/handles/idle.pxd
uvloop/handles/idle.pyx
uvloop/handles/pipe.pxd
uvloop/handles/pipe.pyx
uvloop/handles/poll.pxd
uvloop/handles/poll.pyx
uvloop/handles/process.pxd
uvloop/handles/process.pyx
uvloop/handles/stream.pxd
uvloop/handles/stream.pyx
uvloop/handles/streamserver.pxd
uvloop/handles/streamserver.pyx
uvloop/handles/tcp.pxd
uvloop/handles/tcp.pyx
uvloop/handles/timer.pxd
uvloop/handles/timer.pyx
uvloop/handles/udp.pxd
uvloop/handles/udp.pyx
uvloop/includes/__init__.py
uvloop/includes/compat.h
